{"slug": "semi-equip-front", "name": "半導体製造装置：前工程", "tickers": ["ACLS", "AMAT", "ASML", "KLAC", "LRCX"], "prices": [{"date": "2025-04-15", "ACLS": 47.17, "AMAT": 144.16, "ASML": 677.23, "KLAC": 671.12, "LRCX": 67.94}, {"date": "2025-04-16", "ACLS": 44.62, "AMAT": 136.96, "ASML": 629.42, "KLAC": 637.36, "LRCX": 64.67}, {"date": "2025-04-17", "ACLS": 44.78, "AMAT": 136.24, "ASML": 634.6, "KLAC": 629.66, "LRCX": 63.3}, {"date": "2025-04-21", "ACLS": 45.23, "AMAT": 134.36, "ASML": 619.27, "KLAC": 616.13, "LRCX": 61.94}, {"date": "2025-04-22", "ACLS": 45.1, "AMAT": 137.07, "ASML": 633.15, "KLAC": 631.57, "LRCX": 63.02}, {"date": "2025-04-23", "ACLS": 45.94, "AMAT": 142.31, "ASML": 652.27, "KLAC": 652.17, "LRCX": 66.24}, {"date": "2025-04-24", "ACLS": 48.9, "AMAT": 148.84, "ASML": 669.14, "KLAC": 684.23, "LRCX": 70.38}, {"date": "2025-04-25", "ACLS": 49.84, "AMAT": 150.21, "ASML": 671.39, "KLAC": 689.38, "LRCX": 70.9}, {"date": "2025-04-28", "ACLS": 48.6, "AMAT": 149.45, "ASML": 668.99, "KLAC": 688.5, "LRCX": 71.05}, {"date": "2025-04-29", "ACLS": 47.87, "AMAT": 148.22, "ASML": 662.37, "KLAC": 682.77, "LRCX": 70.38}, {"date": "2025-04-30", "ACLS": 48.98, "AMAT": 149.37, "ASML": 664.33, "KLAC": 697.4, "LRCX": 71.15}, {"date": "2025-05-01", "ACLS": 49.11, "AMAT": 147.64, "ASML": 662.98, "KLAC": 671.22, "LRCX": 71.21}, {"date": "2025-05-02", "ACLS": 52.3, "AMAT": 153.72, "ASML": 686.46, "KLAC": 692.91, "LRCX": 73.98}, {"date": "2025-05-05", "ACLS": 52.09, "AMAT": 153.24, "ASML": 679.53, "KLAC": 688.07, "LRCX": 73.37}, {"date": "2025-05-06", "ACLS": 54.69, "AMAT": 151.67, "ASML": 676.18, "KLAC": 674.31, "LRCX": 72.63}, {"date": "2025-05-07", "ACLS": 58.08, "AMAT": 154.43, "ASML": 696.46, "KLAC": 689.13, "LRCX": 74.51}, {"date": "2025-05-08", "ACLS": 58.86, "AMAT": 154.62, "ASML": 704.06, "KLAC": 698.04, "LRCX": 74.36}, {"date": "2025-05-09", "ACLS": 57.66, "AMAT": 154.23, "ASML": 702.25, "KLAC": 695.92, "LRCX": 74.81}, {"date": "2025-05-12", "ACLS": 62.15, "AMAT": 166.5, "ASML": 745.99, "KLAC": 754.75, "LRCX": 81.65}, {"date": "2025-05-13", "ACLS": 62.86, "AMAT": 171.5, "ASML": 759.62, "KLAC": 789.91, "LRCX": 84.63}, {"date": "2025-05-14", "ACLS": 62.75, "AMAT": 172.6, "ASML": 764.6, "KLAC": 798.94, "LRCX": 84.35}, {"date": "2025-05-15", "ACLS": 62.67, "AMAT": 173.2, "ASML": 754.11, "KLAC": 799.93, "LRCX": 84.17}, {"date": "2025-05-16", "ACLS": 61.58, "AMAT": 164.1, "ASML": 743.9, "KLAC": 785.22, "LRCX": 83.82}, {"date": "2025-05-19", "ACLS": 62.01, "AMAT": 164.47, "ASML": 744.93, "KLAC": 782.97, "LRCX": 83.21}, {"date": "2025-05-20", "ACLS": 62.46, "AMAT": 164.26, "ASML": 744.56, "KLAC": 786.23, "LRCX": 83.68}, {"date": "2025-05-21", "ACLS": 59.07, "AMAT": 160.79, "ASML": 733.04, "KLAC": 774.94, "LRCX": 82.19}, {"date": "2025-05-22", "ACLS": 59.05, "AMAT": 159.55, "ASML": 736.55, "KLAC": 763.57, "LRCX": 81.96}, {"date": "2025-05-23", "ACLS": 58.32, "AMAT": 156.56, "ASML": 728.38, "KLAC": 753.28, "LRCX": 80.47}, {"date": "2025-05-27", "ACLS": 59.67, "AMAT": 160.85, "ASML": 752.55, "KLAC": 785.01, "LRCX": 83.33}, {"date": "2025-05-28", "ACLS": 57.55, "AMAT": 160.61, "ASML": 742.32, "KLAC": 773.51, "LRCX": 83.39}, {"date": "2025-05-29", "ACLS": 58.0, "AMAT": 158.52, "ASML": 742.88, "KLAC": 770.0, "LRCX": 83.55}, {"date": "2025-05-30", "ACLS": 56.34, "AMAT": 155.8, "ASML": 732.64, "KLAC": 752.99, "LRCX": 80.2}, {"date": "2025-06-02", "ACLS": 56.46, "AMAT": 156.32, "ASML": 742.34, "KLAC": 758.52, "LRCX": 81.88}, {"date": "2025-06-03", "ACLS": 59.27, "AMAT": 160.76, "ASML": 743.06, "KLAC": 771.81, "LRCX": 83.05}, {"date": "2025-06-04", "ACLS": 61.49, "AMAT": 160.95, "ASML": 738.61, "KLAC": 778.07, "LRCX": 84.15}, {"date": "2025-06-05", "ACLS": 60.35, "AMAT": 163.2, "ASML": 743.57, "KLAC": 787.82, "LRCX": 84.29}, {"date": "2025-06-06", "ACLS": 63.51, "AMAT": 165.73, "ASML": 748.8, "KLAC": 803.85, "LRCX": 85.72}, {"date": "2025-06-09", "ACLS": 67.61, "AMAT": 168.76, "ASML": 765.88, "KLAC": 825.03, "LRCX": 87.66}, {"date": "2025-06-10", "ACLS": 70.76, "AMAT": 172.72, "ASML": 780.57, "KLAC": 852.19, "LRCX": 90.34}, {"date": "2025-06-11", "ACLS": 67.93, "AMAT": 171.74, "ASML": 779.69, "KLAC": 867.52, "LRCX": 90.29}, {"date": "2025-06-12", "ACLS": 68.91, "AMAT": 173.94, "ASML": 781.8, "KLAC": 870.51, "LRCX": 90.99}, {"date": "2025-06-13", "ACLS": 65.07, "AMAT": 169.56, "ASML": 756.73, "KLAC": 863.21, "LRCX": 88.87}, {"date": "2025-06-16", "ACLS": 68.96, "AMAT": 175.48, "ASML": 770.88, "KLAC": 887.8, "LRCX": 92.73}, {"date": "2025-06-17", "ACLS": 68.48, "AMAT": 173.04, "ASML": 755.6, "KLAC": 888.41, "LRCX": 91.99}, {"date": "2025-06-18", "ACLS": 66.89, "AMAT": 171.79, "ASML": 757.37, "KLAC": 866.69, "LRCX": 91.8}, {"date": "2025-06-20", "ACLS": 66.02, "AMAT": 168.44, "ASML": 752.29, "KLAC": 845.63, "LRCX": 90.06}, {"date": "2025-06-23", "ACLS": 66.53, "AMAT": 170.92, "ASML": 775.35, "KLAC": 851.88, "LRCX": 91.17}, {"date": "2025-06-24", "ACLS": 69.64, "AMAT": 179.09, "ASML": 808.8, "KLAC": 884.46, "LRCX": 95.17}, {"date": "2025-06-25", "ACLS": 70.16, "AMAT": 181.96, "ASML": 810.67, "KLAC": 888.87, "LRCX": 95.56}, {"date": "2025-06-26", "ACLS": 70.92, "AMAT": 182.41, "ASML": 793.61, "KLAC": 898.3, "LRCX": 96.37}, {"date": "2025-06-27", "ACLS": 69.69, "AMAT": 182.1, "ASML": 791.49, "KLAC": 885.3, "LRCX": 96.73}, {"date": "2025-06-30", "ACLS": 69.69, "AMAT": 181.96, "ASML": 796.9, "KLAC": 891.14, "LRCX": 96.87}, {"date": "2025-07-01", "ACLS": 71.99, "AMAT": 182.65, "ASML": 786.04, "KLAC": 894.23, "LRCX": 96.34}, {"date": "2025-07-02", "ACLS": 72.95, "AMAT": 188.86, "ASML": 795.11, "KLAC": 916.37, "LRCX": 98.36}, {"date": "2025-07-03", "ACLS": 73.04, "AMAT": 189.89, "ASML": 790.04, "KLAC": 919.83, "LRCX": 98.34}, {"date": "2025-07-07", "ACLS": 70.95, "AMAT": 189.63, "ASML": 780.69, "KLAC": 907.93, "LRCX": 97.67}, {"date": "2025-07-08", "ACLS": 74.21, "AMAT": 193.81, "ASML": 789.65, "KLAC": 914.5, "LRCX": 99.35}, {"date": "2025-07-09", "ACLS": 74.37, "AMAT": 194.21, "ASML": 795.34, "KLAC": 918.44, "LRCX": 99.33}, {"date": "2025-07-10", "ACLS": 75.65, "AMAT": 196.83, "ASML": 797.59, "KLAC": 923.85, "LRCX": 100.57}, {"date": "2025-07-11", "ACLS": 74.86, "AMAT": 196.73, "ASML": 797.43, "KLAC": 919.83, "LRCX": 101.24}, {"date": "2025-07-14", "ACLS": 71.46, "AMAT": 195.91, "ASML": 802.21, "KLAC": 917.11, "LRCX": 99.14}, {"date": "2025-07-15", "ACLS": 71.75, "AMAT": 198.08, "ASML": 818.4, "KLAC": 931.72, "LRCX": 100.58}, {"date": "2025-07-16", "ACLS": 71.64, "AMAT": 193.63, "ASML": 750.22, "KLAC": 928.7, "LRCX": 99.89}, {"date": "2025-07-17", "ACLS": 71.52, "AMAT": 191.36, "ASML": 740.73, "KLAC": 932.27, "LRCX": 100.31}, {"date": "2025-07-18", "ACLS": 70.96, "AMAT": 189.29, "ASML": 730.46, "KLAC": 926.34, "LRCX": 100.18}, {"date": "2025-07-21", "ACLS": 74.54, "AMAT": 191.45, "ASML": 715.64, "KLAC": 932.94, "LRCX": 101.25}, {"date": "2025-07-22", "ACLS": 75.25, "AMAT": 186.01, "ASML": 701.52, "KLAC": 887.64, "LRCX": 97.22}, {"date": "2025-07-23", "ACLS": 74.84, "AMAT": 185.88, "ASML": 712.91, "KLAC": 892.48, "LRCX": 96.63}, {"date": "2025-07-24", "ACLS": 72.85, "AMAT": 186.98, "ASML": 721.01, "KLAC": 899.54, "LRCX": 97.31}, {"date": "2025-07-25", "ACLS": 73.4, "AMAT": 184.57, "ASML": 707.26, "KLAC": 897.46, "LRCX": 96.49}, {"date": "2025-07-28", "ACLS": 75.38, "AMAT": 189.12, "ASML": 725.9, "KLAC": 918.41, "LRCX": 98.15}, {"date": "2025-07-29", "ACLS": 73.17, "AMAT": 187.27, "ASML": 716.27, "KLAC": 911.39, "LRCX": 98.46}, {"date": "2025-07-30", "ACLS": 72.89, "AMAT": 188.24, "ASML": 719.22, "KLAC": 920.24, "LRCX": 98.61}, {"date": "2025-07-31", "ACLS": 67.69, "AMAT": 178.97, "ASML": 692.57, "KLAC": 874.52, "LRCX": 94.38}, {"date": "2025-08-01", "ACLS": 68.75, "AMAT": 178.9, "ASML": 687.69, "KLAC": 882.09, "LRCX": 95.91}, {"date": "2025-08-04", "ACLS": 70.88, "AMAT": 181.71, "ASML": 697.2, "KLAC": 910.92, "LRCX": 97.94}, {"date": "2025-08-05", "ACLS": 78.01, "AMAT": 178.07, "ASML": 687.5, "KLAC": 878.87, "LRCX": 96.22}, {"date": "2025-08-06", "ACLS": 75.72, "AMAT": 177.06, "ASML": 688.83, "KLAC": 883.72, "LRCX": 95.48}, {"date": "2025-08-07", "ACLS": 79.51, "AMAT": 182.04, "ASML": 710.92, "KLAC": 907.38, "LRCX": 98.67}, {"date": "2025-08-08", "ACLS": 79.42, "AMAT": 183.75, "ASML": 720.09, "KLAC": 910.1, "LRCX": 101.26}, {"date": "2025-08-11", "ACLS": 78.0, "AMAT": 183.26, "ASML": 719.08, "KLAC": 905.51, "LRCX": 101.51}, {"date": "2025-08-12", "ACLS": 81.32, "AMAT": 187.31, "ASML": 739.5, "KLAC": 930.73, "LRCX": 104.77}, {"date": "2025-08-13", "ACLS": 84.97, "AMAT": 188.88, "ASML": 753.24, "KLAC": 944.6, "LRCX": 106.23}, {"date": "2025-08-14", "ACLS": 83.76, "AMAT": 187.1, "ASML": 752.88, "KLAC": 950.5, "LRCX": 106.86}, {"date": "2025-08-15", "ACLS": 80.51, "AMAT": 160.78, "ASML": 739.87, "KLAC": 870.45, "LRCX": 99.03}, {"date": "2025-08-18", "ACLS": 80.73, "AMAT": 162.54, "ASML": 745.24, "KLAC": 880.77, "LRCX": 98.41}, {"date": "2025-08-19", "ACLS": 80.2, "AMAT": 161.24, "ASML": 741.32, "KLAC": 873.48, "LRCX": 99.85}, {"date": "2025-08-20", "ACLS": 79.07, "AMAT": 159.99, "ASML": 747.18, "KLAC": 875.83, "LRCX": 98.67}, {"date": "2025-08-21", "ACLS": 78.51, "AMAT": 159.33, "ASML": 733.13, "KLAC": 869.8, "LRCX": 97.94}, {"date": "2025-08-22", "ACLS": 81.29, "AMAT": 161.97, "ASML": 752.56, "KLAC": 867.69, "LRCX": 99.6}, {"date": "2025-08-25", "ACLS": 80.38, "AMAT": 161.47, "ASML": 752.13, "KLAC": 876.94, "LRCX": 100.79}, {"date": "2025-08-26", "ACLS": 80.91, "AMAT": 163.98, "ASML": 760.84, "KLAC": 885.46, "LRCX": 103.13}, {"date": "2025-08-27", "ACLS": 81.92, "AMAT": 163.86, "ASML": 767.62, "KLAC": 886.25, "LRCX": 103.17}, {"date": "2025-08-28", "ACLS": 82.01, "AMAT": 164.74, "ASML": 761.1, "KLAC": 891.34, "LRCX": 103.59}, {"date": "2025-08-29", "ACLS": 80.04, "AMAT": 160.25, "ASML": 740.33, "KLAC": 869.41, "LRCX": 99.67}, {"date": "2025-09-02", "ACLS": 79.6, "AMAT": 157.07, "ASML": 723.61, "KLAC": 843.84, "LRCX": 96.56}, {"date": "2025-09-03", "ACLS": 78.69, "AMAT": 155.75, "ASML": 734.55, "KLAC": 841.39, "LRCX": 97.27}, {"date": "2025-09-04", "ACLS": 78.79, "AMAT": 157.73, "ASML": 751.1, "KLAC": 870.7, "LRCX": 99.94}, {"date": "2025-09-05", "ACLS": 80.61, "AMAT": 162.23, "ASML": 779.29, "KLAC": 902.4, "LRCX": 102.46}, {"date": "2025-09-08", "ACLS": 81.82, "AMAT": 161.53, "ASML": 793.79, "KLAC": 906.28, "LRCX": 104.57}, {"date": "2025-09-09", "ACLS": 83.08, "AMAT": 162.98, "ASML": 802.65, "KLAC": 915.0, "LRCX": 105.06}, {"date": "2025-09-10", "ACLS": 83.28, "AMAT": 162.9, "ASML": 790.69, "KLAC": 929.86, "LRCX": 106.84}, {"date": "2025-09-11", "ACLS": 86.36, "AMAT": 169.61, "ASML": 801.68, "KLAC": 956.43, "LRCX": 115.02}, {"date": "2025-09-12", "ACLS": 85.55, "AMAT": 167.26, "ASML": 811.36, "KLAC": 961.16, "LRCX": 116.4}, {"date": "2025-09-15", "ACLS": 87.3, "AMAT": 170.38, "ASML": 864.62, "KLAC": 985.97, "LRCX": 118.64}, {"date": "2025-09-16", "ACLS": 89.81, "AMAT": 172.98, "ASML": 875.71, "KLAC": 987.63, "LRCX": 119.89}, {"date": "2025-09-17", "ACLS": 91.1, "AMAT": 177.56, "ASML": 869.58, "KLAC": 986.93, "LRCX": 121.31}, {"date": "2025-09-18", "ACLS": 96.66, "AMAT": 189.15, "ASML": 924.94, "KLAC": 1043.58, "LRCX": 125.71}, {"date": "2025-09-19", "ACLS": 95.65, "AMAT": 189.49, "ASML": 929.27, "KLAC": 1041.71, "LRCX": 126.31}, {"date": "2025-09-22", "ACLS": 100.44, "AMAT": 199.88, "ASML": 954.84, "KLAC": 1068.07, "LRCX": 131.56}, {"date": "2025-09-23", "ACLS": 98.47, "AMAT": 200.23, "ASML": 960.54, "KLAC": 1068.02, "LRCX": 131.3}, {"date": "2025-09-24", "ACLS": 97.16, "AMAT": 200.8, "ASML": 944.02, "KLAC": 1065.5, "LRCX": 127.96}, {"date": "2025-09-25", "ACLS": 97.13, "AMAT": 198.96, "ASML": 946.62, "KLAC": 1055.95, "LRCX": 127.77}, {"date": "2025-09-26", "ACLS": 97.48, "AMAT": 203.27, "ASML": 948.58, "KLAC": 1061.13, "LRCX": 127.97}, {"date": "2025-09-29", "ACLS": 96.7, "AMAT": 204.29, "ASML": 959.64, "KLAC": 1060.97, "LRCX": 130.72}, {"date": "2025-09-30", "ACLS": 97.64, "AMAT": 204.08, "ASML": 965.1, "KLAC": 1075.4, "LRCX": 133.52}, {"date": "2025-10-01", "ACLS": 94.76, "AMAT": 217.04, "ASML": 1000.17, "KLAC": 1125.52, "LRCX": 142.38}, {"date": "2025-10-02", "ACLS": 93.57, "AMAT": 222.87, "ASML": 1026.99, "KLAC": 1135.88, "LRCX": 146.57}, {"date": "2025-10-03", "ACLS": 88.71, "AMAT": 216.83, "ASML": 1029.03, "KLAC": 1098.28, "LRCX": 145.4}, {"date": "2025-10-06", "ACLS": 87.69, "AMAT": 223.19, "ASML": 1040.08, "KLAC": 1136.32, "LRCX": 148.73}, {"date": "2025-10-07", "ACLS": 83.66, "AMAT": 210.88, "ASML": 999.21, "KLAC": 1081.52, "LRCX": 139.95}, {"date": "2025-10-08", "ACLS": 84.47, "AMAT": 216.81, "ASML": 984.76, "KLAC": 1059.43, "LRCX": 142.14}, {"date": "2025-10-09", "ACLS": 84.61, "AMAT": 219.6, "ASML": 977.51, "KLAC": 1050.34, "LRCX": 140.6}, {"date": "2025-10-10", "ACLS": 79.19, "AMAT": 209.28, "ASML": 933.3, "KLAC": 979.83, "LRCX": 131.0}, {"date": "2025-10-13", "ACLS": 81.43, "AMAT": 218.78, "ASML": 981.62, "KLAC": 1021.96, "LRCX": 137.42}, {"date": "2025-10-14", "ACLS": 80.38, "AMAT": 217.49, "ASML": 980.15, "KLAC": 1022.66, "LRCX": 137.92}, {"date": "2025-10-15", "ACLS": 83.77, "AMAT": 226.85, "ASML": 1006.69, "KLAC": 1083.78, "LRCX": 144.37}, {"date": "2025-10-16", "ACLS": 83.62, "AMAT": 226.99, "ASML": 1016.44, "KLAC": 1095.54, "LRCX": 141.97}, {"date": "2025-10-17", "ACLS": 82.88, "AMAT": 224.27, "ASML": 1026.09, "KLAC": 1103.37, "LRCX": 141.11}, {"date": "2025-10-20", "ACLS": 83.88, "AMAT": 227.4, "ASML": 1038.93, "KLAC": 1149.47, "LRCX": 143.64}, {"date": "2025-10-21", "ACLS": 83.29, "AMAT": 225.28, "ASML": 1021.86, "KLAC": 1144.02, "LRCX": 144.63}, {"date": "2025-10-22", "ACLS": 81.4, "AMAT": 219.85, "ASML": 1008.45, "KLAC": 1111.01, "LRCX": 140.85}, {"date": "2025-10-23", "ACLS": 84.36, "AMAT": 227.74, "ASML": 1033.21, "KLAC": 1155.56, "LRCX": 147.12}, {"date": "2025-10-24", "ACLS": 83.31, "AMAT": 228.02, "ASML": 1029.91, "KLAC": 1179.31, "LRCX": 151.25}, {"date": "2025-10-27", "ACLS": 83.25, "AMAT": 230.59, "ASML": 1056.71, "KLAC": 1211.52, "LRCX": 156.45}, {"date": "2025-10-28", "ACLS": 82.29, "AMAT": 226.91, "ASML": 1049.23, "KLAC": 1202.46, "LRCX": 155.18}, {"date": "2025-10-29", "ACLS": 83.14, "AMAT": 235.0, "ASML": 1069.43, "KLAC": 1231.61, "LRCX": 160.21}, {"date": "2025-10-30", "ACLS": 81.84, "AMAT": 231.81, "ASML": 1074.03, "KLAC": 1210.8, "LRCX": 160.55}, {"date": "2025-10-31", "ACLS": 79.56, "AMAT": 232.35, "ASML": 1057.83, "KLAC": 1205.15, "LRCX": 157.01}, {"date": "2025-11-03", "ACLS": 82.74, "AMAT": 236.95, "ASML": 1065.41, "KLAC": 1215.52, "LRCX": 160.78}, {"date": "2025-11-04", "ACLS": 80.51, "AMAT": 229.45, "ASML": 1028.78, "KLAC": 1189.94, "LRCX": 155.34}, {"date": "2025-11-05", "ACLS": 84.45, "AMAT": 240.12, "ASML": 1042.38, "KLAC": 1223.45, "LRCX": 164.58}, {"date": "2025-11-06", "ACLS": 82.14, "AMAT": 232.78, "ASML": 1027.84, "KLAC": 1202.82, "LRCX": 161.73}, {"date": "2025-11-07", "ACLS": 85.74, "AMAT": 229.33, "ASML": 1015.62, "KLAC": 1189.82, "LRCX": 158.9}, {"date": "2025-11-10", "ACLS": 87.42, "AMAT": 234.33, "ASML": 1037.42, "KLAC": 1214.33, "LRCX": 165.9}, {"date": "2025-11-11", "ACLS": 85.58, "AMAT": 227.94, "ASML": 1021.07, "KLAC": 1187.36, "LRCX": 158.73}, {"date": "2025-11-12", "ACLS": 85.42, "AMAT": 229.99, "ASML": 1035.96, "KLAC": 1195.41, "LRCX": 160.96}, {"date": "2025-11-13", "ACLS": 82.62, "AMAT": 222.52, "ASML": 1018.52, "KLAC": 1158.27, "LRCX": 152.88}, {"date": "2025-11-14", "ACLS": 81.54, "AMAT": 225.29, "ASML": 1005.65, "KLAC": 1130.95, "LRCX": 147.84}, {"date": "2025-11-17", "ACLS": 80.53, "AMAT": 227.98, "ASML": 1018.66, "KLAC": 1132.23, "LRCX": 147.04}, {"date": "2025-11-18", "ACLS": 77.7, "AMAT": 224.4, "ASML": 1002.74, "KLAC": 1121.63, "LRCX": 142.83}, {"date": "2025-11-19", "ACLS": 77.85, "AMAT": 234.38, "ASML": 1037.96, "KLAC": 1165.94, "LRCX": 148.38}, {"date": "2025-11-20", "ACLS": 74.12, "AMAT": 219.96, "ASML": 979.75, "KLAC": 1101.02, "LRCX": 139.19}, {"date": "2025-11-21", "ACLS": 76.88, "AMAT": 223.73, "ASML": 965.3, "KLAC": 1095.7, "LRCX": 142.25}, {"date": "2025-11-24", "ACLS": 78.89, "AMAT": 230.62, "ASML": 986.52, "KLAC": 1135.25, "LRCX": 149.95}, {"date": "2025-11-25", "ACLS": 82.75, "AMAT": 242.16, "ASML": 1001.9, "KLAC": 1144.4, "LRCX": 151.5}, {"date": "2025-11-26", "ACLS": 82.13, "AMAT": 249.66, "ASML": 1039.6, "KLAC": 1157.57, "LRCX": 154.7}, {"date": "2025-11-28", "ACLS": 82.77, "AMAT": 251.94, "ASML": 1058.6, "KLAC": 1173.94, "LRCX": 155.56}, {"date": "2025-12-01", "ACLS": 81.51, "AMAT": 254.43, "ASML": 1086.56, "KLAC": 1155.68, "LRCX": 154.35}, {"date": "2025-12-02", "ACLS": 82.43, "AMAT": 265.0, "ASML": 1107.32, "KLAC": 1188.32, "LRCX": 157.74}, {"date": "2025-12-03", "ACLS": 88.02, "AMAT": 268.3, "ASML": 1139.42, "KLAC": 1210.18, "LRCX": 159.56}, {"date": "2025-12-04", "ACLS": 89.1, "AMAT": 269.1, "ASML": 1108.62, "KLAC": 1206.51, "LRCX": 156.9}, {"date": "2025-12-05", "ACLS": 90.82, "AMAT": 267.67, "ASML": 1098.02, "KLAC": 1212.88, "LRCX": 158.51}, {"date": "2025-12-08", "ACLS": 91.14, "AMAT": 267.83, "ASML": 1118.21, "KLAC": 1223.0, "LRCX": 162.55}, {"date": "2025-12-09", "ACLS": 88.95, "AMAT": 266.81, "ASML": 1109.98, "KLAC": 1224.02, "LRCX": 165.61}, {"date": "2025-12-10", "ACLS": 90.34, "AMAT": 274.81, "ASML": 1117.85, "KLAC": 1237.3, "LRCX": 168.06}, {"date": "2025-12-11", "ACLS": 89.08, "AMAT": 269.77, "ASML": 1121.36, "KLAC": 1244.56, "LRCX": 168.51}, {"date": "2025-12-12", "ACLS": 85.61, "AMAT": 258.89, "ASML": 1079.43, "KLAC": 1192.37, "LRCX": 160.33}, {"date": "2025-12-15", "ACLS": 87.26, "AMAT": 260.94, "ASML": 1086.39, "KLAC": 1223.52, "LRCX": 164.1}, {"date": "2025-12-16", "ACLS": 86.32, "AMAT": 258.52, "ASML": 1074.63, "KLAC": 1221.78, "LRCX": 163.06}, {"date": "2025-12-17", "ACLS": 81.65, "AMAT": 247.96, "ASML": 1014.09, "KLAC": 1170.5, "LRCX": 154.79}, {"date": "2025-12-18", "ACLS": 81.13, "AMAT": 253.18, "ASML": 1034.94, "KLAC": 1220.8, "LRCX": 164.5}, {"date": "2025-12-19", "ACLS": 82.72, "AMAT": 256.09, "ASML": 1054.63, "KLAC": 1244.05, "LRCX": 172.06}, {"date": "2025-12-22", "ACLS": 83.15, "AMAT": 258.69, "ASML": 1055.59, "KLAC": 1264.02, "LRCX": 175.05}, {"date": "2025-12-23", "ACLS": 83.7, "AMAT": 259.91, "ASML": 1060.44, "KLAC": 1267.1, "LRCX": 174.95}, {"date": "2025-12-24", "ACLS": 82.8, "AMAT": 260.46, "ASML": 1064.12, "KLAC": 1275.33, "LRCX": 177.12}, {"date": "2025-12-26", "ACLS": 82.61, "AMAT": 261.57, "ASML": 1071.34, "KLAC": 1277.94, "LRCX": 177.86}, {"date": "2025-12-29", "ACLS": 81.82, "AMAT": 262.72, "ASML": 1064.6, "KLAC": 1258.75, "LRCX": 175.66}, {"date": "2025-12-30", "ACLS": 81.55, "AMAT": 259.65, "ASML": 1070.73, "KLAC": 1242.04, "LRCX": 173.57}, {"date": "2025-12-31", "ACLS": 80.34, "AMAT": 256.67, "ASML": 1068.45, "KLAC": 1213.5, "LRCX": 170.98}, {"date": "2026-01-02", "ACLS": 86.12, "AMAT": 268.54, "ASML": 1162.25, "KLAC": 1272.82, "LRCX": 184.84}, {"date": "2026-01-05", "ACLS": 89.04, "AMAT": 283.97, "ASML": 1226.57, "KLAC": 1350.69, "LRCX": 194.53}, {"date": "2026-01-06", "ACLS": 93.9, "AMAT": 295.64, "ASML": 1240.55, "KLAC": 1393.19, "LRCX": 206.71}, {"date": "2026-01-07", "ACLS": 92.99, "AMAT": 291.84, "ASML": 1226.85, "KLAC": 1357.93, "LRCX": 202.84}, {"date": "2026-01-08", "ACLS": 89.89, "AMAT": 281.29, "ASML": 1192.75, "KLAC": 1322.88, "LRCX": 200.72}, {"date": "2026-01-09", "ACLS": 93.1, "AMAT": 300.8, "ASML": 1272.2, "KLAC": 1398.18, "LRCX": 218.1}, {"date": "2026-01-12", "ACLS": 95.72, "AMAT": 306.86, "ASML": 1279.54, "KLAC": 1426.32, "LRCX": 220.14}, {"date": "2026-01-13", "ACLS": 97.04, "AMAT": 304.49, "ASML": 1268.49, "KLAC": 1439.95, "LRCX": 214.12}, {"date": "2026-01-14", "ACLS": 93.22, "AMAT": 301.51, "ASML": 1262.06, "KLAC": 1432.64, "LRCX": 208.54}, {"date": "2026-01-15", "ACLS": 96.5, "AMAT": 318.68, "ASML": 1329.85, "KLAC": 1542.96, "LRCX": 217.21}, {"date": "2026-01-16", "ACLS": 93.12, "AMAT": 326.6, "ASML": 1356.78, "KLAC": 1565.79, "LRCX": 222.69}, {"date": "2026-01-20", "ACLS": 88.16, "AMAT": 317.83, "ASML": 1324.32, "KLAC": 1484.25, "LRCX": 222.14}, {"date": "2026-01-21", "ACLS": 93.42, "AMAT": 324.83, "ASML": 1358.3, "KLAC": 1518.03, "LRCX": 228.12}, {"date": "2026-01-22", "ACLS": 94.96, "AMAT": 318.39, "ASML": 1393.16, "KLAC": 1498.05, "LRCX": 220.44}, {"date": "2026-01-23", "ACLS": 91.12, "AMAT": 321.98, "ASML": 1387.21, "KLAC": 1510.82, "LRCX": 217.68}, {"date": "2026-01-26", "ACLS": 89.17, "AMAT": 319.06, "ASML": 1411.49, "KLAC": 1541.03, "LRCX": 222.6}, {"date": "2026-01-27", "ACLS": 91.04, "AMAT": 332.3, "ASML": 1452.67, "KLAC": 1614.23, "LRCX": 238.17}, {"date": "2026-01-28", "ACLS": 91.23, "AMAT": 336.33, "ASML": 1421.05, "KLAC": 1625.09, "LRCX": 239.29}, {"date": "2026-01-29", "ACLS": 92.2, "AMAT": 340.91, "ASML": 1453.24, "KLAC": 1682.52, "LRCX": 247.87}, {"date": "2026-01-30", "ACLS": 88.07, "AMAT": 321.92, "ASML": 1421.13, "KLAC": 1426.09, "LRCX": 233.18}, {"date": "2026-02-02", "ACLS": 88.81, "AMAT": 327.99, "ASML": 1439.49, "KLAC": 1408.62, "LRCX": 237.22}, {"date": "2026-02-03", "ACLS": 84.37, "AMAT": 318.27, "ASML": 1394.04, "KLAC": 1353.78, "LRCX": 229.82}, {"date": "2026-02-04", "ACLS": 82.76, "AMAT": 297.23, "ASML": 1337.37, "KLAC": 1305.52, "LRCX": 209.53}, {"date": "2026-02-05", "ACLS": 81.49, "AMAT": 303.61, "ASML": 1348.38, "KLAC": 1329.3, "LRCX": 213.05}, {"date": "2026-02-06", "ACLS": 86.08, "AMAT": 322.11, "ASML": 1411.15, "KLAC": 1441.08, "LRCX": 230.73}, {"date": "2026-02-09", "ACLS": 85.47, "AMAT": 330.16, "ASML": 1427.61, "KLAC": 1438.29, "LRCX": 229.01}, {"date": "2026-02-10", "ACLS": 89.05, "AMAT": 328.66, "ASML": 1413.62, "KLAC": 1428.98, "LRCX": 226.34}, {"date": "2026-02-11", "ACLS": 91.82, "AMAT": 339.46, "ASML": 1435.63, "KLAC": 1477.58, "LRCX": 234.84}, {"date": "2026-02-12", "ACLS": 90.54, "AMAT": 327.98, "ASML": 1406.87, "KLAC": 1448.97, "LRCX": 231.01}, {"date": "2026-02-13", "ACLS": 94.55, "AMAT": 354.47, "ASML": 1406.61, "KLAC": 1462.23, "LRCX": 235.25}, {"date": "2026-02-17", "ACLS": 98.5, "AMAT": 358.68, "ASML": 1419.78, "KLAC": 1470.19, "LRCX": 235.3}, {"date": "2026-02-18", "ACLS": 82.01, "AMAT": 368.84, "ASML": 1468.72, "KLAC": 1480.3, "LRCX": 239.8}, {"date": "2026-02-19", "ACLS": 80.62, "AMAT": 369.83, "ASML": 1458.93, "KLAC": 1469.9, "LRCX": 237.11}, {"date": "2026-02-20", "ACLS": 80.16, "AMAT": 375.38, "ASML": 1469.59, "KLAC": 1496.0, "LRCX": 244.63}, {"date": "2026-02-23", "ACLS": 78.79, "AMAT": 373.55, "ASML": 1485.99, "KLAC": 1487.66, "LRCX": 241.98}, {"date": "2026-02-24", "ACLS": 81.77, "AMAT": 377.93, "ASML": 1497.8, "KLAC": 1506.65, "LRCX": 243.96}, {"date": "2026-02-25", "ACLS": 80.02, "AMAT": 394.95, "ASML": 1526.51, "KLAC": 1546.68, "LRCX": 249.18}, {"date": "2026-02-26", "ACLS": 83.58, "AMAT": 375.72, "ASML": 1463.8, "KLAC": 1524.31, "LRCX": 238.78}, {"date": "2026-02-27", "ACLS": 82.61, "AMAT": 372.3, "ASML": 1450.56, "KLAC": 1524.55, "LRCX": 233.61}, {"date": "2026-03-02", "ACLS": 86.58, "AMAT": 372.18, "ASML": 1423.54, "KLAC": 1534.95, "LRCX": 230.72}, {"date": "2026-03-03", "ACLS": 85.88, "AMAT": 351.32, "ASML": 1360.94, "KLAC": 1441.35, "LRCX": 217.01}, {"date": "2026-03-04", "ACLS": 86.62, "AMAT": 357.76, "ASML": 1399.37, "KLAC": 1475.91, "LRCX": 222.99}, {"date": "2026-03-05", "ACLS": 85.91, "AMAT": 346.53, "ASML": 1368.36, "KLAC": 1429.36, "LRCX": 214.68}, {"date": "2026-03-06", "ACLS": 82.24, "AMAT": 324.74, "ASML": 1292.8, "KLAC": 1344.55, "LRCX": 199.33}, {"date": "2026-03-09", "ACLS": 84.06, "AMAT": 338.94, "ASML": 1357.42, "KLAC": 1429.1, "LRCX": 211.15}, {"date": "2026-03-10", "ACLS": 85.82, "AMAT": 345.88, "ASML": 1383.4, "KLAC": 1452.94, "LRCX": 215.23}, {"date": "2026-03-11", "ACLS": 86.22, "AMAT": 351.07, "ASML": 1386.68, "KLAC": 1465.0, "LRCX": 218.87}, {"date": "2026-03-12", "ACLS": 85.18, "AMAT": 337.27, "ASML": 1351.58, "KLAC": 1409.57, "LRCX": 209.49}, {"date": "2026-03-13", "ACLS": 83.19, "AMAT": 341.53, "ASML": 1345.69, "KLAC": 1418.64, "LRCX": 212.2}, {"date": "2026-03-16", "ACLS": 84.55, "AMAT": 346.18, "ASML": 1375.56, "KLAC": 1438.24, "LRCX": 219.4}, {"date": "2026-03-17", "ACLS": 85.15, "AMAT": 352.46, "ASML": 1389.16, "KLAC": 1481.35, "LRCX": 226.47}, {"date": "2026-03-18", "ACLS": 85.74, "AMAT": 349.47, "ASML": 1355.17, "KLAC": 1482.36, "LRCX": 224.71}, {"date": "2026-03-19", "ACLS": 87.12, "AMAT": 357.21, "ASML": 1366.39, "KLAC": 1511.52, "LRCX": 233.99}, {"date": "2026-03-20", "ACLS": 84.43, "AMAT": 357.06, "ASML": 1317.25, "KLAC": 1498.67, "LRCX": 228.36}, {"date": "2026-03-23", "ACLS": 85.77, "AMAT": 361.79, "ASML": 1369.62, "KLAC": 1511.43, "LRCX": 233.31}, {"date": "2026-03-24", "ACLS": 94.39, "AMAT": 373.99, "ASML": 1399.42, "KLAC": 1566.19, "LRCX": 238.84}, {"date": "2026-03-25", "ACLS": 100.85, "AMAT": 369.34, "ASML": 1393.89, "KLAC": 1543.82, "LRCX": 233.45}, {"date": "2026-03-26", "ACLS": 98.35, "AMAT": 338.55, "ASML": 1329.5, "KLAC": 1451.13, "LRCX": 211.62}, {"date": "2026-03-27", "ACLS": 97.35, "AMAT": 337.17, "ASML": 1302.47, "KLAC": 1443.21, "LRCX": 211.41}, {"date": "2026-03-30", "ACLS": 90.43, "AMAT": 323.12, "ASML": 1253.96, "KLAC": 1382.58, "LRCX": 199.93}, {"date": "2026-03-31", "ACLS": 93.08, "AMAT": 341.79, "ASML": 1320.83, "KLAC": 1472.41, "LRCX": 213.66}, {"date": "2026-04-01", "ACLS": 95.51, "AMAT": 353.8, "ASML": 1359.76, "KLAC": 1519.84, "LRCX": 222.01}, {"date": "2026-04-02", "ACLS": 95.09, "AMAT": 348.47, "ASML": 1317.23, "KLAC": 1516.84, "LRCX": 218.44}, {"date": "2026-04-06", "ACLS": 97.5, "AMAT": 352.62, "ASML": 1304.01, "KLAC": 1540.06, "LRCX": 220.65}, {"date": "2026-04-07", "ACLS": 96.87, "AMAT": 354.31, "ASML": 1306.45, "KLAC": 1548.85, "LRCX": 224.35}, {"date": "2026-04-08", "ACLS": 104.65, "AMAT": 385.72, "ASML": 1421.05, "KLAC": 1672.34, "LRCX": 246.49}, {"date": "2026-04-09", "ACLS": 108.24, "AMAT": 397.81, "ASML": 1448.64, "KLAC": 1727.26, "LRCX": 258.76}, {"date": "2026-04-10", "ACLS": 110.37, "AMAT": 399.49, "ASML": 1478.28, "KLAC": 1737.28, "LRCX": 263.66}, {"date": "2026-04-13", "ACLS": 110.74, "AMAT": 395.73, "ASML": 1500.2, "KLAC": 1768.78, "LRCX": 267.32}, {"date": "2026-04-14", "ACLS": 113.06, "AMAT": 395.64, "ASML": 1518.3, "KLAC": 1795.91, "LRCX": 272.41}, {"date": "2026-04-15", "ACLS": 117.88, "AMAT": 394.26, "ASML": 1481.77, "KLAC": 1748.11, "LRCX": 265.16}, {"date": "2026-04-16", "ACLS": 118.76, "AMAT": 389.9, "ASML": 1410.83, "KLAC": 1734.85, "LRCX": 260.96}]}