{"company_name": "カナディアン・ナショナル鉄道", "industry_name": "陸上輸送", "themes": [{"10日": 0.0518, "1ヶ月": 0.0015, "1年": 0.3367, "1日": 0.017, "2ヶ月": 0.0157, "3ヶ月": 0.1059, "5日": 0.0327, "color_num": null, "comments": "カナダ全土と米国中西部をカバーする大陸横断鉄道。大西洋・太平洋・メキシコ湾の三つの海岸線にアクセス可能で、資源や工業製品の輸出入を支える物流インフラ。", "industry": "資本財", "is_special": false, "name": "鉄道貨物", "related": "CNI,CP,CSX,NSC,UNP", "slug": "railways", "text": "", "theme1": "物流", "theme2": "鉄道貨物", "theme_no": 75, "tickerPerformances": {"CNI": {"10日": 0.0663, "1ヶ月": 0.0035, "1年": 0.1373, "1日": 0.0165, "2ヶ月": 0.0834, "3ヶ月": 0.0769, "5日": 0.0476, "半年": 0.1214}, "CP": {"10日": 0.0326, "1ヶ月": -0.0248, "1年": 0.1657, "1日": 0.0196, "2ヶ月": 0.0347, "3ヶ月": 0.1138, "5日": 0.038, "半年": 0.0577}, "CSX": {"10日": 0.0841, "1ヶ月": 0.0379, "1年": 0.5723, "1日": 0.0174, "2ヶ月": 0.0604, "3ヶ月": 0.1721, "5日": 0.0266, "半年": 0.1706}, "NSC": {"10日": 0.0369, "1ヶ月": -0.0275, "1年": 0.4227, "1日": 0.0194, "2ヶ月": -0.0375, "3ヶ月": 0.0146, "5日": 0.0247, "半年": -0.0094}, "UNP": {"10日": 0.0394, "1ヶ月": -0.0177, "1年": 0.1957, "1日": 0.0122, "2ヶ月": -0.0041, "3ヶ月": 0.0719, "5日": 0.0267, "半年": 0.0609}}, "半年": 0.0897}], "ticker": "CNI"}