{"data":[{"close":88.38,"date":"2021-05-01"},{"close":91.24,"date":"2021-06-01"},{"close":92.39,"date":"2021-07-01"},{"close":92.39,"date":"2021-08-01"},{"close":81.78,"date":"2021-09-01"},{"close":82.76,"date":"2021-10-01"},{"close":79.7,"date":"2021-11-01"},{"close":87.47,"date":"2021-12-01"},{"close":86.91,"date":"2022-01-01"},{"close":87.46,"date":"2022-02-01"},{"close":87.75,"date":"2022-03-01"},{"close":88.029999,"date":"2022-04-01"},{"close":90.94,"date":"2022-05-01"},{"close":84.53,"date":"2022-06-01"},{"close":85.83,"date":"2022-07-01"},{"close":80.52,"date":"2022-08-01"},{"close":76.010002,"date":"2022-09-01"},{"close":81.13,"date":"2022-10-01"},{"close":89.56,"date":"2022-11-01"},{"close":90.72,"date":"2022-12-01"},{"close":90.62,"date":"2023-01-01"},{"close":84.12,"date":"2023-02-01"},{"close":92.0,"date":"2023-03-01"},{"close":102.57,"date":"2023-04-01"},{"close":96.25,"date":"2023-05-01"},{"close":100.91,"date":"2023-06-01"},{"close":104.9,"date":"2023-07-01"},{"close":100.48,"date":"2023-08-01"},{"close":101.86,"date":"2023-09-01"},{"close":93.58,"date":"2023-10-01"},{"close":97.9,"date":"2023-11-01"},{"close":100.97,"date":"2023-12-01"},{"close":103.47,"date":"2024-01-01"},{"close":100.97,"date":"2024-02-01"},{"close":96.73,"date":"2024-03-01"},{"close":97.13,"date":"2024-04-01"},{"close":103.13,"date":"2024-05-01"},{"close":106.46,"date":"2024-06-01"},{"close":111.48,"date":"2024-07-01"},{"close":120.89,"date":"2024-08-01"},{"close":115.019997,"date":"2024-09-01"},{"close":108.4,"date":"2024-10-01"},{"close":105.77,"date":"2024-11-01"},{"close":97.31,"date":"2024-12-01"},{"close":104.72,"date":"2025-01-01"},{"close":109.050003,"date":"2025-02-01"},{"close":111.48,"date":"2025-03-01"},{"close":113.49,"date":"2025-04-01"},{"close":115.76,"date":"2025-05-01"},{"close":121.010002,"date":"2025-06-01"},{"close":113.74,"date":"2025-07-01"},{"close":126.55,"date":"2025-08-01"},{"close":128.24001,"date":"2025-09-01"},{"close":123.79,"date":"2025-10-01"},{"close":130.39999,"date":"2025-11-01"},{"close":137.87,"date":"2025-12-01"},{"close":148.67999,"date":"2026-01-01"},{"close":168.62,"date":"2026-02-01"},{"close":152.75,"date":"2026-03-01"},{"close":154.42,"date":"2026-04-01"}]}
