{"data": [{"close": 9.96, "date": "2021-05-01"}, {"close": 10.17, "date": "2021-06-01"}, {"close": 9.87, "date": "2021-07-01"}, {"close": 9.91, "date": "2021-08-01"}, {"close": 9.9, "date": "2021-09-01"}, {"close": 10.32, "date": "2021-10-01"}, {"close": 10.2, "date": "2021-11-01"}, {"close": 9.95, "date": "2021-12-01"}, {"close": 8.18, "date": "2022-01-01"}, {"close": 4.7, "date": "2022-02-01"}, {"close": 9.05, "date": "2022-03-01"}, {"close": 6.44, "date": "2022-04-01"}, {"close": 6.78, "date": "2022-05-01"}, {"close": 3.93, "date": "2022-06-01"}, {"close": 4.61, "date": "2022-07-01"}, {"close": 4.74, "date": "2022-08-01"}, {"close": 4.88, "date": "2022-09-01"}, {"close": 6.01, "date": "2022-10-01"}, {"close": 5.06, "date": "2022-11-01"}, {"close": 3.15, "date": "2022-12-01"}, {"close": 3.3, "date": "2023-01-01"}, {"close": 3.23, "date": "2023-02-01"}, {"close": 2.95, "date": "2023-03-01"}, {"close": 1.63, "date": "2023-04-01"}, {"close": 1.51, "date": "2023-05-01"}, {"close": 2.44, "date": "2023-06-01"}, {"close": 3.14, "date": "2023-07-01"}, {"close": 2.11, "date": "2023-08-01"}, {"close": 2.27, "date": "2023-09-01"}, {"close": 1.81, "date": "2023-10-01"}, {"close": 2.13, "date": "2023-11-01"}, {"close": 1.83, "date": "2023-12-01"}, {"close": 1.31, "date": "2024-01-01"}, {"close": 1.77, "date": "2024-02-01"}, {"close": 1.68, "date": "2024-03-01"}, {"close": 1.58, "date": "2024-04-01"}, {"close": 1.25, "date": "2024-05-01"}, {"close": 1.25, "date": "2024-06-01"}, {"close": 1.23, "date": "2024-07-01"}, {"close": 1.07, "date": "2024-08-01"}, {"close": 0.63999999, "date": "2024-09-01"}, {"close": 0.47299999, "date": "2024-10-01"}, {"close": 0.34999999, "date": "2024-11-01"}, {"close": 2.19, "date": "2024-12-01"}, {"close": 1.18, "date": "2025-01-01"}, {"close": 0.66299999, "date": "2025-02-01"}, {"close": 0.52100003, "date": "2025-03-01"}, {"close": 0.89899999, "date": "2025-04-01"}, {"close": 0.90899998, "date": "2025-05-01"}, {"close": 0.88800001, "date": "2025-06-01"}, {"close": 1.3, "date": "2025-07-01"}, {"close": 1.09, "date": "2025-08-01"}, {"close": 1.67, "date": "2025-09-01"}, {"close": 2.36, "date": "2025-10-01"}, {"close": 1.97, "date": "2025-11-01"}, {"close": 1.8, "date": "2025-12-01"}, {"close": 2.03, "date": "2026-01-01"}, {"close": 1.64, "date": "2026-02-01"}, {"close": 0.96200001, "date": "2026-03-01"}, {"close": 0.98000002, "date": "2026-04-01"}]}