{"data": [{"close": 49.22, "date": "2021-05-01"}, {"close": 47.68, "date": "2021-06-01"}, {"close": 48.040001, "date": "2021-07-01"}, {"close": 50.23, "date": "2021-08-01"}, {"close": 45.52, "date": "2021-09-01"}, {"close": 44.11, "date": "2021-10-01"}, {"close": 42.64, "date": "2021-11-01"}, {"close": 47.39, "date": "2021-12-01"}, {"close": 50.88, "date": "2022-01-01"}, {"close": 51.29, "date": "2022-02-01"}, {"close": 52.25, "date": "2022-03-01"}, {"close": 55.57, "date": "2022-04-01"}, {"close": 54.09, "date": "2022-05-01"}, {"close": 41.77, "date": "2022-06-01"}, {"close": 43.86, "date": "2022-07-01"}, {"close": 45.12, "date": "2022-08-01"}, {"close": 40.38, "date": "2022-09-01"}, {"close": 46.27, "date": "2022-10-01"}, {"close": 46.58, "date": "2022-11-01"}, {"close": 45.71, "date": "2022-12-01"}, {"close": 45.040001, "date": "2023-01-01"}, {"close": 46.43, "date": "2023-02-01"}, {"close": 44.62, "date": "2023-03-01"}, {"close": 47.51, "date": "2023-04-01"}, {"close": 44.42, "date": "2023-05-01"}, {"close": 45.3, "date": "2023-06-01"}, {"close": 45.42, "date": "2023-07-01"}, {"close": 44.22, "date": "2023-08-01"}, {"close": 42.049999, "date": "2023-09-01"}, {"close": 40.17, "date": "2023-10-01"}, {"close": 42.040001, "date": "2023-11-01"}, {"close": 40.34, "date": "2023-12-01"}, {"close": 40.12, "date": "2024-01-01"}, {"close": 40.91, "date": "2024-02-01"}, {"close": 43.62, "date": "2024-03-01"}, {"close": 43.81, "date": "2024-04-01"}, {"close": 46.25, "date": "2024-05-01"}, {"close": 45.55, "date": "2024-06-01"}, {"close": 49.0099983, "date": "2024-07-01"}, {"close": 53.77, "date": "2024-08-01"}, {"close": 51.040001, "date": "2024-09-01"}, {"close": 54.46, "date": "2024-10-01"}, {"close": 57.74, "date": "2024-11-01"}, {"close": 52.29, "date": "2024-12-01"}, {"close": 52.23, "date": "2025-01-01"}, {"close": 55.85, "date": "2025-02-01"}, {"close": 60.02, "date": "2025-03-01"}, {"close": 59.15, "date": "2025-04-01"}, {"close": 60.61, "date": "2025-05-01"}, {"close": 58.63, "date": "2025-06-01"}, {"close": 61.94, "date": "2025-07-01"}, {"close": 67.21, "date": "2025-08-01"}, {"close": 66.059998, "date": "2025-09-01"}, {"close": 56.38, "date": "2025-10-01"}, {"close": 59.0099983, "date": "2025-11-01"}, {"close": 57.66, "date": "2025-12-01"}, {"close": 61.99, "date": "2026-01-01"}, {"close": 69.040001, "date": "2026-02-01"}, {"close": 65.99, "date": "2026-03-01"}, {"close": 66.8, "date": "2026-04-01"}]}